Metadata-Version: 2.1
Name: deeprank2
Version: 3.1.0
Summary: DeepRank2 is an open-source deep learning framework for data mining of protein-protein interfaces or single-residue missense variants.
Author: Daniel Rademaker, Gayatri Ramakrishnan, Sven van der Burg, Li Xue, Daniil Lepikhov
Author-email: Giulia Crocioni <g.crocioni@esciencecenter.nl>, Coos Baakman <coos.baakman@radboudumc.nl>, Dani Bodor <d.bodor@esciencecenter.nl>
License: Apache-2.0 license
Project-URL: Documentation, https://deeprank2.readthedocs.io/en/latest/?badge=latest
Project-URL: Repository, https://github.com/DeepRank/deeprank2
Project-URL: Changelog, https://github.com/DeepRank/deeprank2/blob/main/CHANGELOG.md
Keywords: graph neural network,convolutional neural network,protein-protein interfaces,missense variants,deep learning,pytorch
Classifier: Intended Audience :: Developers
Classifier: License :: OSI Approved :: Apache Software License
Classifier: Natural Language :: English
Classifier: Programming Language :: Python :: 3
Classifier: Programming Language :: Python :: 3.10
Requires-Python: >=3.10
License-File: LICENSE
License-File: NOTICE
Requires-Dist: notebook <8.0,>=7.2.1
Requires-Dist: markov-clustering <1.0,>=0.0.6.dev0
Requires-Dist: tensorboard <3.0,>=0.9.0
Requires-Dist: protobuf <6.0,>=3.20.1
Requires-Dist: dill <1.0,>=0.3.8
Requires-Dist: pyarrow <17.0,>=16.1.0
Requires-Dist: tables <4.0,>=3.9.2
Requires-Dist: numpy <2.0,>=1.25
Requires-Dist: scipy <2.0,>=1.13.1
Requires-Dist: h5py <4.0,>=3.11.0
Requires-Dist: networkx <4.0,>=3.1
Requires-Dist: matplotlib <4.0,>=3.9.0
Requires-Dist: scikit-learn <2.0,>=1.5.0
Requires-Dist: chart-studio <2.0,>=1.1.0
Requires-Dist: pdb2sql <1.0,>=0.5.3
Requires-Dist: python-louvain <1.0,>=0.16
Requires-Dist: tqdm <5.0,>=4.66.4
Requires-Dist: freesasa <3.0,>=2.1.1
Requires-Dist: biopython <2.0,>=1.83
Provides-Extra: notebooks
Requires-Dist: nbmake ; extra == 'notebooks'
Provides-Extra: publishing
Requires-Dist: build ; extra == 'publishing'
Requires-Dist: twine ; extra == 'publishing'
Requires-Dist: wheel ; extra == 'publishing'
Provides-Extra: test
Requires-Dist: pytest <8.0,>=7.4.0 ; extra == 'test'
Requires-Dist: bump-my-version <1.0,>=0.24.2 ; extra == 'test'
Requires-Dist: coverage <7.0,>=6.5.0 ; extra == 'test'
Requires-Dist: pycodestyle <3.0,>=2.8.0 ; extra == 'test'
Requires-Dist: pytest-cov <5.0,>=4.1.0 ; extra == 'test'
Requires-Dist: pytest-runner <7.0,>=6.0.0 ; extra == 'test'
Requires-Dist: coveralls <4.0,>=3.3.1 ; extra == 'test'
Requires-Dist: ruff ==0.6.3 ; extra == 'test'
